ytbpy/__init__.py
ytbpy/channel.py
ytbpy/playlist.py
ytbpy/search.py
ytbpy/utils.py
ytbpy/video.py
ytbpy-0.1.1.dist-info/licenses/LICENSE
ytbpy-0.1.1.dist-info/METADATA
ytbpy-0.1.1.dist-info/WHEEL
ytbpy-0.1.1.dist-info/top_level.txt
ytbpy-0.1.1.dist-info/RECORD
