Metadata-Version: 2.4
Name: ytbpy
Version: 0.1.1
Summary: A fast, lightweight Python library for extracting information from YouTube without requiring API keys
Author-email: TN3W <tn3w@protonmail.com>
License-Expression: Apache-2.0
Project-URL: Homepage, https://github.com/tn3w/ytbpy
Project-URL: Documentation, https://github.com/tn3w/ytbpy
Project-URL: Repository, https://github.com/tn3w/ytbpy.git
Project-URL: Issues, https://github.com/tn3w/ytbpy/issues
Keywords: youtube,api,scraper,video,playlist,channel,search
Classifier: Development Status :: 4 - Beta
Classifier: Environment :: Web Environment
Classifier: Intended Audience :: Developers
Classifier: Operating System :: OS Independent
Classifier: Programming Language :: Python
Classifier: Programming Language :: Python :: 3
Classifier: Programming Language :: Python :: 3.6
Classifier: Programming Language :: Python :: 3.7
Classifier: Programming Language :: Python :: 3.8
Classifier: Programming Language :: Python :: 3.9
Classifier: Programming Language :: Python :: 3.10
Classifier: Programming Language :: Python :: 3.11
Classifier: Topic :: Internet :: WWW/HTTP
Classifier: Topic :: Multimedia :: Video
Requires-Python: >=3.6
License-File: LICENSE
Dynamic: license-file
